{
  "restaurant": {
    "name": "Acaxee",
    "version": "2026",
    "total_tables": 42,
    "total_capacity": 240
  },
  "seat_rules": {
    "2":  { "min_persons": 1, "max_persons": 2 },
    "4":  { "min_persons": 1, "max_persons": 4 },
    "6":  { "min_persons": 3, "max_persons": 6 },
    "8":  { "min_persons": 6, "max_persons": 8 },
    "10": { "min_persons": 6, "max_persons": 10 }
  },
  "zones": {
    "A": { "name": "Barra lateral izquierda", "description": "Mesas intimas y medianas" },
    "B": { "name": "Rectangulares centro-izquierda", "description": "Grupos y familias" },
    "C": { "name": "Redondas grandes superiores", "description": "Grupos grandes, celebraciones" },
    "D": { "name": "Centro del salon", "description": "Mesas para 2, intimas" },
    "E": { "name": "Centro-derecha", "description": "Mesas para 2, intimas" },
    "F": { "name": "Columna rectangulares derecha", "description": "Mesas para 2-4" },
    "G": { "name": "Redondas extremo derecho", "description": "Desde intimas hasta eventos" }
  },
  "tables": {
    "1":  { "zone": "A", "seats": 2,  "shape": "round_small" },
    "2":  { "zone": "A", "seats": 2,  "shape": "round_small" },
    "3":  { "zone": "A", "seats": 2,  "shape": "round_small" },
    "4":  { "zone": "A", "seats": 4,  "shape": "rect_small" },
    "5":  { "zone": "A", "seats": 6,  "shape": "rect_medium" },
    "6":  { "zone": "A", "seats": 4,  "shape": "round_medium" },
    "7":  { "zone": "A", "seats": 4,  "shape": "round_medium" },
    "21": { "zone": "B", "seats": 8,  "shape": "rect_large" },
    "22": { "zone": "B", "seats": 8,  "shape": "rect_large" },
    "23": { "zone": "B", "seats": 8,  "shape": "rect_large" },
    "24": { "zone": "B", "seats": 8,  "shape": "rect_large" },
    "25": { "zone": "B", "seats": 4,  "shape": "rect_small" },
    "26": { "zone": "C", "seats": 10, "shape": "round_large" },
    "27": { "zone": "C", "seats": 10, "shape": "round_large" },
    "28": { "zone": "C", "seats": 10, "shape": "round_large" },
    "31": { "zone": "D", "seats": 4,  "shape": "round_medium" },
    "32": { "zone": "D", "seats": 4,  "shape": "round_medium" },
    "33": { "zone": "D", "seats": 4,  "shape": "round_medium" },
    "34": { "zone": "D", "seats": 4,  "shape": "round_medium" },
    "35": { "zone": "D", "seats": 4,  "shape": "round_medium" },
    "36": { "zone": "D", "seats": 4,  "shape": "round_medium" },
    "41": { "zone": "E", "seats": 4,  "shape": "round_medium" },
    "42": { "zone": "E", "seats": 4,  "shape": "round_medium" },
    "43": { "zone": "E", "seats": 4,  "shape": "round_medium" },
    "44": { "zone": "E", "seats": 4,  "shape": "round_medium" },
    "45": { "zone": "E", "seats": 4,  "shape": "round_medium" },
    "46": { "zone": "E", "seats": 4,  "shape": "round_medium" },
    "51": { "zone": "F", "seats": 4,  "shape": "round_medium" },
    "52": { "zone": "F", "seats": 4,  "shape": "rect_small" },
    "53": { "zone": "F", "seats": 4,  "shape": "rect_small" },
    "54": { "zone": "F", "seats": 4,  "shape": "rect_small" },
    "55": { "zone": "F", "seats": 4,  "shape": "rect_small" },
    "56": { "zone": "C", "seats": 10, "shape": "round_large" },
    "57": { "zone": "C", "seats": 10, "shape": "round_large" },
    "58": { "zone": "C", "seats": 10, "shape": "round_large" },
    "61": { "zone": "G", "seats": 4,  "shape": "round_medium" },
    "62": { "zone": "G", "seats": 4,  "shape": "round_medium" },
    "63": { "zone": "G", "seats": 10, "shape": "round_large" },
    "64": { "zone": "G", "seats": 10, "shape": "round_large" },
    "65": { "zone": "G", "seats": 10, "shape": "round_large" },
    "66": { "zone": "G", "seats": 10, "shape": "round_large" },
    "67": { "zone": "G", "seats": 4,  "shape": "round_medium" }
  }
}
